{
  "sets": {
    "N5": [
      {
        "id": "n5-r1",
        "source": "N5R p1",
        "title": "아침 식사",
        "korean": "늦잠을 자서 아침을 못 먹고 학교에 간 상황이에요.",
        "tone": "tone-coral",
        "passageStyle": "plain",
        "passage": [
          "わたしは 毎朝 ご飯となっとうか、パンとたまごを 食べて、学校へ 行きます。",
          "でも、けさは 何も 食べませんでした。バナナを 学校へ 持って 行きました。",
          "起きた 時間が おそかったからです。"
        ],
        "question": "けさ「わたし」は 学校へ 行く 前に、何を 食べましたか。",
        "options": [
          "ご飯となっとうを 食べました。",
          "パンとたまごを 食べました。",
          "何も 食べませんでした。",
          "バナナを 食べました。"
        ],
        "answer": 2,
        "explanation": "늦게 일어나서 학교 가기 전에 아무것도 못 먹었고, 바나나는 학교에 가져갔어요."
      },
      {
        "id": "n5-r2",
        "source": "N5R p2",
        "title": "수업 공지",
        "korean": "일본어 1반 학생에게 전하는 공지예요.",
        "tone": "tone-gold",
        "passageStyle": "note",
        "passage": [
          "「日本語１」と「日本語２」の クラスの みなさんへ",
          "今日 出川先生は お昼まで お休みです。午前の「日本語１」の クラスは ありません。",
          "午後の「日本語２」の クラスは あります。",
          "・「日本語１」の しゅくだいは 来週 出してください。"
        ],
        "question": "大学は「日本語１」の クラスの 学生に 何を 言いたいですか。",
        "options": [
          "今日 クラスは ありません。しゅくだいは 午後 出してください。",
          "今日 クラスは ありません。しゅくだいは 来週 出してください。",
          "今日 クラスが ありますが、しゅくだいは 来週 出してください。",
          "今日 クラスが ありますから、しゅくだいを 出してください。"
        ],
        "answer": 1,
        "explanation": "일본어 1반은 오전 수업이 없고, 숙제는 다음 주에 내라고 알려주고 있어요."
      },
      {
        "id": "n5-r3",
        "source": "N5R p3",
        "title": "메모 확인",
        "korean": "우체국 사람이 오기 전에 뭘 먼저 해야 하는지 묻는 메모 문제예요.",
        "tone": "tone-sky",
        "passageStyle": "note",
        "passage": [
          "ボゴさん",
          "10時ごろ ゆうびんきょくの 人が この にもつを とりに 来ますから、にもつと お金を わたして ください。",
          "お金は 中西さんが 持って います。ゆうびんきょくの 人が 来る 前に もらいに 行って ください。",
          "よろしく おねがいします。"
        ],
        "question": "この メモを 読んで、ボゴさんは はじめに 何を しますか。",
        "options": [
          "中西さんに お金を もらいます。",
          "中西さんに にもつと お金を わたします。",
          "ゆうびんきょくの 人に にもつを もらいます。",
          "ゆうびんきょくの 人に にもつと お金を わたします。"
        ],
        "answer": 0,
        "explanation": "우체국 사람이 오기 전에 먼저 중西さん에게서 돈을 받아 와야 해요."
      },
      {
        "id": "n5-r4",
        "source": "N5 PDF q18",
        "title": "ねこの世話",
        "korean": "고양이 돌봄 분담을 읽고 수요일에 '나'가 할 일을 고르는 문제예요.",
        "tone": "tone-coral",
        "passageStyle": "plain",
        "passage": [
          "うちにはねこがいます。ねこのトイレそうじはずっと私がしてきましたが、来月から妹がすることになりました。ごはんはいつも弟があげていますが、弟は水曜日にテニスのれんしゅうに行くので、その日は私があげています。日曜日は母の仕事がないので、トイレそうじもごはんをあげることもぜんぶ母がしています。"
        ],
        "question": "「私」は来月の水曜日、何をしますか。",
        "options": [
          "ねこのトイレそうじをします。",
          "ねこにごはんをあげます。",
          "テニスのれんしゅうに行きます。",
          "仕事をしに行きます。"
        ],
        "answer": 1,
        "explanation": "동생이 수요일에는 테니스 연습에 가기 때문에 그날만 '나'가 고양이에게 밥을 줍니다."
      },
      {
        "id": "n5-r5",
        "source": "N5 PDF q19",
        "title": "家のしょうかい",
        "korean": "집 소개문을 읽고 조건에 맞는 그림 설명을 고르는 문제예요.",
        "tone": "tone-gold",
        "passageStyle": "plain",
        "passage": [
          "私の家をしょうかいします。まず、二階に窓が二つあります。そして、げんかんの横に大きな木が一本あります。いつかは自分の車がほしいですが、今は一台の車を家族みんなで使っています。"
        ],
        "question": "「私」の家はどれですか。",
        "options": [
          "車が一台あり、大きい木が一本あって、えんとつがある家",
          "車が一台あり、木が二本ある家",
          "車が二台あり、木が二本ある家",
          "車が一台あり、大きい木が一本あって、えんとつがない家"
        ],
        "answer": 3,
        "explanation": "본문 조건은 2층 창문 두 개, 현관 옆 큰 나무 한 그루, 차 한 대입니다. 이 조건을 모두 만족하는 것은 4번이에요."
      },
      {
        "id": "n5-r6",
        "source": "N5 PDF q20",
        "title": "たこやきパーティー 1",
        "korean": "타코야키 파티 글을 읽고 첸 씨가 걱정한 이유를 고르는 문제예요.",
        "tone": "tone-sky",
        "passageStyle": "plain",
        "passage": [
          "これはチェンさんが書いたさくぶんです。",
          "たこやきパーティー",
          "先週、友だちの家でたこやきを作って食べる「たこやきパーティー」をしました。私はたこやきが好きでよく買って食べますが、自分で作るのははじめてでした。自分で作るたこやきにはたこをたくさん入れることができて、店のたこやきよりおいしかったです。",
          "また、たこのかわりにチョコレートやクリームなど、甘いものを入れて新しい味のたこやきも作りました。まずくないかな、としんぱいしましたが、思ったよりおいしかったです。",
          "「たこやきパーティー」で友だちといっしょに好きなものを作ってたくさん食べることができてよかったです。それで、こういうパーティーをまたやりたいと思いました。"
        ],
        "question": "チェンさんはなぜしんぱいしましたか。",
        "options": [
          "はじめてたこやきを食べたから",
          "はじめてたこやきを作ったから",
          "たこやきに甘いものを入れたから",
          "たこやきにたこをたくさん入れたから"
        ],
        "answer": 2,
        "explanation": "걱정한 이유는 초콜릿과 크림처럼 단 재료를 넣은 새 맛의 타코야키가 맛없을까 봐서였습니다."
      },
      {
        "id": "n5-r7",
        "source": "N5 PDF q21",
        "title": "たこやきパーティー 2",
        "korean": "타코야키 파티 글을 읽고 다시 하고 싶은 이유를 고르는 문제예요.",
        "tone": "tone-mint",
        "passageStyle": "plain",
        "passage": [
          "これはチェンさんが書いたさくぶんです。",
          "たこやきパーティー",
          "先週、友だちの家でたこやきを作って食べる「たこやきパーティー」をしました。私はたこやきが好きでよく買って食べますが、自分で作るのははじめてでした。自分で作るたこやきにはたこをたくさん入れることができて、店のたこやきよりおいしかったです。",
          "また、たこのかわりにチョコレートやクリームなど、甘いものを入れて新しい味のたこやきも作りました。まずくないかな、としんぱいしましたが、思ったよりおいしかったです。",
          "「たこやきパーティー」で友だちといっしょに好きなものを作ってたくさん食べることができてよかったです。それで、こういうパーティーをまたやりたいと思いました。"
        ],
        "question": "こういうパーティーをまたやりたいと思ったのはどうしてですか。",
        "options": [
          "安くたこやきを作ることができるから",
          "好きなものを入れてたこやきを作るから",
          "自分の家でたこやきを作ってみたいから",
          "友だちとたこやきを作ることができるから"
        ],
        "answer": 3,
        "explanation": "친구들과 함께 좋아하는 재료를 넣고 많이 먹을 수 있어서 좋았기 때문에 다시 하고 싶다고 말합니다."
      },
      {
        "id": "n5-r8",
        "source": "N5 PDF q22",
        "title": "スーパーの営業時間",
        "korean": "영업시간 안내를 보고 조건에 맞는 가게를 찾는 문제예요.",
        "tone": "tone-coral",
        "passageStyle": "note",
        "passage": [
          "営業時間のお知らせ タカダスーパー",
          "【川上店】 3月31日(水)まで 9:00-20:00 / 4月1日(木)から 9:00-21:00",
          "【大山店】 3月31日(水)まで 8:30-20:30 / 4月1日(木)から 9:00-22:00",
          "【下田店】 4月30日(金)まで 9:00-20:30 / 5月1日(土)から 8:30-21:30",
          "【木下店】 4月30日(金)まで 9:00-21:00 / 5月1日(土)から 9:00-20:00"
        ],
        "question": "さきさんはどの店に行きますか。",
        "options": [
          "川上店",
          "大山店",
          "下田店",
          "木下店"
        ],
        "answer": 1,
        "explanation": "4월 1일부터 영어 수업이 끝나는 9시 30분 이후에도 영업하는 곳은 오후 10시까지 여는 大山店뿐입니다."
      }
    ],
    "N4": [
      {
        "id": "n4-r1",
        "source": "N4R p1",
        "title": "분실물 안내",
        "korean": "시험 기간에 분실물을 찾으러 가는 방법을 묻는 공지예요.",
        "tone": "tone-coral",
        "passageStyle": "note",
        "passage": [
          "忘れ物がありました",
          "忘れた人は、先生たちの部屋へ 取りに 来てください。",
          "① 辞書（103教室にありました）",
          "② 帽子（食堂にありました）",
          "12月5日（月）から 7日（水）までは、試験中ですから、先生たちの部屋には 入れません。",
          "教室で クラスの 先生に 言ってください。"
        ],
        "question": "試験中の３日間に 忘れ物を 取りに 行きたい 人は、どうしなければ なりませんか。",
        "options": [
          "試験が 終わるまで 待ちます。",
          "先生たちの 部屋へ 取りに 行きます。",
          "忘れ物が あった 場所へ 取りに 行きます。",
          "教室で、自分の クラスの 先生に 話します。"
        ],
        "answer": 3,
        "explanation": "시험 기간에는 선생님 방에 들어갈 수 없어서 교실에서 자기 반 선생님에게 말해야 해요."
      },
      {
        "id": "n4-r2",
        "source": "N4R p2",
        "title": "겨울 아이스크림",
        "korean": "글쓴이가 뭘 즐거움으로 느끼는지 파악하는 문제예요.",
        "tone": "tone-gold",
        "passageStyle": "plain",
        "passage": [
          "アイスクリームは、夏に 食べると とても おいしいですが、私は 寒い 冬でも 時々 食べます。",
          "夏は 毎日 食べるので 安い ものしか 買いませんが、冬は 高い ものを 買います。",
          "暖かい 部屋で いい アイスクリームを 食べるのが、私の 楽しみなのです。"
        ],
        "question": "私の 楽しみは 何ですか。",
        "options": [
          "冬に 暖かい 部屋で 毎日 アイスクリームを 食べること",
          "冬に 暖かい 部屋で 高い アイスクリームを 食べること",
          "夏に 毎日 アイスクリームを 食べること",
          "夏に 高い アイスクリームを 食べること"
        ],
        "answer": 1,
        "explanation": "글쓴이는 겨울에 따뜻한 방에서 좋은 아이스크림을 먹는 걸 즐거움이라고 말해요."
      },
      {
        "id": "n4-r3",
        "source": "N4R p3",
        "title": "공장 견학 메모",
        "korean": "견학 날짜와 시간, 인원 수까지 함께 알려야 하는 메모예요.",
        "tone": "tone-sky",
        "passageStyle": "note",
        "passage": [
          "高田先生",
          "みそ工場の 林さんから 電話が ありました。",
          "1月に 工場見学が できるのは、19日（木）10時、11時と 26日（木）14時、15時だそうです。",
          "見学の 日と 時間が 決まったら、電話が ほしいと 言っていました。",
          "行く 人の 数も 教えて もらいたいそうです。"
        ],
        "question": "この メモを 読んで、高田先生は 林さんに 何を 知らせなければ なりませんか。",
        "options": [
          "工場見学に 行く 人の 数だけ",
          "工場見学に 行く 日と 時間だけ",
          "工場見学に 行く 日と 時間と、行く 人の 数",
          "工場見学に 行く 日と 時間が、いつごろ 決まるか"
        ],
        "answer": 2,
        "explanation": "메모에는 날짜와 시간뿐 아니라 가는 사람 수까지 알려 달라고 적혀 있어요."
      },
      {
        "id": "n4-r4",
        "source": "N4R p4",
        "title": "검은 지우개",
        "korean": "글쓴이가 검은 지우개를 산 이유를 찾는 짧은 독해예요.",
        "tone": "tone-mint",
        "passageStyle": "plain",
        "passage": [
          "昨日 初めて 黒い 消しゴムを 買いました。",
          "レジの 人が「白いのは、使うと 消しゴムが 黒く 汚れて いやだと 言う 人が 多いから、黒いのを 作ったそうですよ。」と 教えてくれました。",
          "私は 色が かっこいいから 買ったので、理由を 聞いて おもしろいなと 思いました。"
        ],
        "question": "「私」は どうして 黒い 消しゴムを 買いましたか。",
        "options": [
          "黒い 消しゴムは、使った 後で 汚れないから",
          "黒い 消しゴムを 買う 人が 多いと 店の 人に 聞いたから",
          "黒い 消しゴムの ほうが 字を きれいに 消せるから",
          "黒い 消しゴムは、色が かっこいいと 思ったから"
        ],
        "answer": 3,
        "explanation": "글쓴이는 성능 때문이 아니라 색이 멋있다고 생각해서 샀다고 말해요."
      },
      {
        "id": "n4-r5",
        "source": "N4 PDF q22",
        "title": "ストレスとの付き合い方",
        "korean": "스트레스를 멀리 둔다는 표현이 무엇인지 묻는 문제예요.",
        "tone": "tone-coral",
        "passageStyle": "plain",
        "passage": [
          "私はストレスがあるとき、カフェでコーヒーを飲みながら、本を読みます。本を読んでいると、本のストーリーで頭がいっぱいになります。だから、そのときはストレスを遠くに置くことができます。ストレスがきれいになくなることではありませんが、ストレスについて考える時間が減ります。少しの間、ストレスを頭の中から出すことで、心は楽になります。"
        ],
        "question": "ストレスを遠くに置くことは、どういうことですか。",
        "options": [
          "ストレスで頭がいっぱいになること",
          "ストレスがきれいになくなること",
          "ストレスについて考えないこと",
          "ストレスを楽に考えること"
        ],
        "answer": 2,
        "explanation": "글쓴이는 스트레스를 완전히 없애는 것이 아니라, 잠시라도 스트레스에 대해 생각하지 않게 되는 상태를 말합니다."
      },
      {
        "id": "n4-r6",
        "source": "N4 PDF q23",
        "title": "美術館のお知らせ",
        "korean": "미술관 안내문을 읽고 맞는 설명을 고르는 문제예요.",
        "tone": "tone-gold",
        "passageStyle": "note",
        "passage": [
          "美術館の利用について",
          "開館時間：午前11時から午後7時まで（受付は美術館が閉まる30分前までです）",
          "休み：毎週月曜日、最後の週の火曜日",
          "料金：大人800円 / 子ども300円 / 5才以下は無料",
          "注意① 美術館の中に食べ物や飲み物を持って入らないこと",
          "注意② 美術館の作品は触らないこと。写真もだめです。"
        ],
        "question": "このお知らせから、美術館についてわかることは何ですか。",
        "options": [
          "美術館は7時半まで開いています。",
          "5才の子どもは300円はらいます。",
          "美術館の中で飲み物を飲んでもいいです。",
          "美術館の作品の写真を撮ってはいけません。"
        ],
        "answer": 3,
        "explanation": "안내문에 '사진도 안 됩니다'라고 적혀 있으므로 작품 사진 촬영 금지가 정답입니다."
      },
      {
        "id": "n4-r7",
        "source": "N4 PDF q24",
        "title": "旅行会社の仕事",
        "korean": "여행회사에서 하는 일을 읽고 하지 않는 일을 고르는 문제예요.",
        "tone": "tone-sky",
        "passageStyle": "plain",
        "passage": [
          "高橋さんは旅行会社で働いています。会社に着くと、まず自分のテーブルをかたづけます。それから自分の仕事をします。お客さまの旅行の予約をしたり、旅行の計画の相談を受けたりします。分からないことは先輩たちが教えてくれます。また旅行から帰ってきたお客さまに連絡をして、困ったことがなかったか話も聞きます。"
        ],
        "question": "高橋さんが会社でしないことはどれですか。",
        "options": [
          "テーブルをかたづけます。",
          "お客さまの旅行の予約をします。",
          "先輩に旅行の相談をします。",
          "旅行から帰ったお客さまに連絡します。"
        ],
        "answer": 2,
        "explanation": "선배는 모르는 것을 가르쳐 주는 사람이지, 다카하시 씨가 선배에게 여행 상담을 하는 내용은 아닙니다."
      },
      {
        "id": "n4-r8",
        "source": "N4 PDF q25",
        "title": "スマホとの距離 1",
        "korean": "스마트폰 글을 읽고 'それ'가 가리키는 내용을 고르는 문제예요.",
        "tone": "tone-mint",
        "passageStyle": "plain",
        "passage": [
          "これはシャオ・メイさんが書いた作文です。",
          "スマホ",
          "私は国にいたとき、1日8時間以上スマホを使っていました。スマホで行うのは友だちとのメールやSNS、おもしろい動画を見ることなどでした。いつも手に持っていたので、友だちからの連絡にすぐに返事をしていました。友だちもすぐに返事をくれるので、それが普通だと思っていました。",
          "日本に来て、日本人の友だちができました。「家に遊びに来ない？」と連絡してみると、返事が来たのは数時間後でした。友だちのメールには「別のことをしていて、返事が遅くなった。」と書いてありました。友だちは私のことが嫌いなんだと悲しくなりました。しかし、このようなことが数回あって、日本人はスマホよりも自分の時間を大切にしていることが分かりました。自分の時間を自由に楽しんでいることです。私は私の時間がいつもスマホといっしょにあることに気づきました。",
          "そこで、私はスマホを触らない時間を作ることにしました。すると、本を読んだり、映画を見たりするなど、自分の時間ができました。何も考えないで、不必要にスマホを触っているときよりも幸せな時間です。今は意識的にスマホを使わない時間を作って、がまんしていますが、これからは（　　　）なりたいです。"
        ],
        "question": "それは何ですか。",
        "options": [
          "スマホを1日8時間以上使うこと",
          "友だちとメールやSNSをすること",
          "おもしろい動画を見ること",
          "友だちからの連絡にすぐ返事すること"
        ],
        "answer": 3,
        "explanation": "앞문장에서 친구들의 연락에 바로 답장하는 것이 보통이라고 생각했다고 했으므로 'それ'는 즉시 답장하는 일을 가리킵니다."
      },
      {
        "id": "n4-r9",
        "source": "N4 PDF q26",
        "title": "スマホとの距離 2",
        "korean": "스마트폰 글을 읽고 '나'가 슬퍼진 이유를 고르는 문제예요.",
        "tone": "tone-coral",
        "passageStyle": "plain",
        "passage": [
          "これはシャオ・メイさんが書いた作文です。",
          "スマホ",
          "私は国にいたとき、1日8時間以上スマホを使っていました。スマホで行うのは友だちとのメールやSNS、おもしろい動画を見ることなどでした。いつも手に持っていたので、友だちからの連絡にすぐに返事をしていました。友だちもすぐに返事をくれるので、それが普通だと思っていました。",
          "日本に来て、日本人の友だちができました。「家に遊びに来ない？」と連絡してみると、返事が来たのは数時間後でした。友だちのメールには「別のことをしていて、返事が遅くなった。」と書いてありました。友だちは私のことが嫌いなんだと悲しくなりました。しかし、このようなことが数回あって、日本人はスマホよりも自分の時間を大切にしていることが分かりました。自分の時間を自由に楽しんでいることです。私は私の時間がいつもスマホといっしょにあることに気づきました。",
          "そこで、私はスマホを触らない時間を作ることにしました。すると、本を読んだり、映画を見たりするなど、自分の時間ができました。何も考えないで、不必要にスマホを触っているときよりも幸せな時間です。今は意識的にスマホを使わない時間を作って、がまんしていますが、これからは（　　　）なりたいです。"
        ],
        "question": "なぜ、「私」は悲しくなりましたか。",
        "options": [
          "友だちが家に遊びに来なかったから",
          "友だちが「私」を嫌いだと思ったから",
          "友だちから返事が来なかったから",
          "友だちが「私」にあやまらなかったから"
        ],
        "answer": 1,
        "explanation": "일본 친구의 답장이 늦자 '나를 싫어하나 보다'라고 생각해서 슬퍼졌다고 본문에 나옵니다."
      },
      {
        "id": "n4-r10",
        "source": "N4 PDF q27",
        "title": "スマホとの距離 3",
        "korean": "스마트폰 글의 마지막 빈칸에 들어갈 표현을 고르는 문제예요.",
        "tone": "tone-gold",
        "passageStyle": "plain",
        "passage": [
          "これはシャオ・メイさんが書いた作文です。",
          "スマホ",
          "私は国にいたとき、1日8時間以上スマホを使っていました。スマホで行うのは友だちとのメールやSNS、おもしろい動画を見ることなどでした。いつも手に持っていたので、友だちからの連絡にすぐに返事をしていました。友だちもすぐに返事をくれるので、それが普通だと思っていました。",
          "日本に来て、日本人の友だちができました。「家に遊びに来ない？」と連絡してみると、返事が来たのは数時間後でした。友だちのメールには「別のことをしていて、返事が遅くなった。」と書いてありました。友だちは私のことが嫌いなんだと悲しくなりました。しかし、このようなことが数回あって、日本人はスマホよりも自分の時間を大切にしていることが分かりました。自分の時間を自由に楽しんでいることです。私は私の時間がいつもスマホといっしょにあることに気づきました。",
          "そこで、私はスマホを触らない時間を作ることにしました。すると、本を読んだり、映画を見たりするなど、自分の時間ができました。何も考えないで、不必要にスマホを触っているときよりも幸せな時間です。今は意識的にスマホを使わない時間を作って、がまんしていますが、これからは（　　　）なりたいです。"
        ],
        "question": "（　　　）に入れるのに、いちばんいい文はどれですか。",
        "options": [
          "自分で必要なときだけスマホを使えるように",
          "自由な時間がなくなるように",
          "スマホをたくさん使えるように",
          "ほかのことをする時間を減らせるように"
        ],
        "answer": 0,
        "explanation": "앞뒤 문맥상 앞으로는 '필요할 때만 스마트폰을 쓰게 되고 싶다'가 가장 자연스럽습니다."
      },
      {
        "id": "n4-r11",
        "source": "N4 PDF q28",
        "title": "学生寮の案内 1",
        "korean": "기숙사 안내표를 보고 조던 씨가 고를 수 있는 곳을 찾는 문제예요.",
        "tone": "tone-sky",
        "passageStyle": "note",
        "passage": [
          "学生寮の案内",
          "【さくら】1人部屋 / 30,000円 / 食事なし",
          "【あさがお】1人部屋 / 55,000円 / 朝と夜",
          "【もみじ】2人部屋 / 42,000円 / 朝と夜",
          "【ひかり】2人部屋 / 32,000円 / 夜",
          "【にじ】3人部屋 / 38,000円 / 朝と夜",
          "【みどり】4人部屋 / 25,000円 / 夜",
          "「さくら」と「あさがお」以外はトイレが部屋についていません。",
          "「さくら」は部屋にキッチンがついています。その他の部屋では料理ができません。"
        ],
        "question": "ジョーダンさんが選べるのはどれですか。",
        "options": [
          "「ひかり」",
          "「にじ」",
          "「ひかり」と「みどり」",
          "「にじ」と「みどり」"
        ],
        "answer": 2,
        "explanation": "저녁 식사가 가능하고 3만 5천 엔 이하인 곳은 ひかり와 みどり 두 곳입니다."
      },
      {
        "id": "n4-r12",
        "source": "N4 PDF q29",
        "title": "学生寮の案内 2",
        "korean": "기숙사 안내표를 보고 지혜 씨 조건에 맞는 곳을 찾는 문제예요.",
        "tone": "tone-mint",
        "passageStyle": "note",
        "passage": [
          "学生寮の案内",
          "【さくら】1人部屋 / 30,000円 / 食事なし",
          "【あさがお】1人部屋 / 55,000円 / 朝と夜",
          "【もみじ】2人部屋 / 42,000円 / 朝と夜",
          "【ひかり】2人部屋 / 32,000円 / 夜",
          "【にじ】3人部屋 / 38,000円 / 朝と夜",
          "【みどり】4人部屋 / 25,000円 / 夜",
          "「さくら」と「あさがお」以外はトイレが部屋についていません。",
          "「さくら」は部屋にキッチンがついています。その他の部屋では料理ができません。"
        ],
        "question": "ジヘさんが選べるのはどれですか。",
        "options": [
          "「さくら」",
          "「あさがお」",
          "「もみじ」と「ひかり」",
          "「あさがお」と「もみじ」"
        ],
        "answer": 1,
        "explanation": "1인실 또는 2인실, 방 안 화장실, 식사 제공이라는 조건을 모두 만족하는 곳은 あさがお뿐입니다."
      }
    ],
    "N3": [
      {
        "id": "n3-r1",
        "source": "N3R p1",
        "title": "폭설 안내 메일",
        "korean": "오전 수업 취소와 오후 수업 여부 공지를 어떻게 이해해야 할지 묻고 있어요.",
        "tone": "tone-coral",
        "passageStyle": "note",
        "passage": [
          "件名: 大雪による休講のお知らせ",
          "現在、大雪のため、多くの公共交通機関が止まっています。そのため、午前の授業は行われません。",
          "午後の授業は、10時までに公共交通機関が動き始めれば、いつもの通り行います。",
          "授業を行うかどうか10時にメールでお知らせしますので、必ず確認してください。"
        ],
        "question": "このメールから わかることは 何ですか。",
        "options": [
          "今日の 午前の 授業は、10時から 始まる。",
          "午前も 午後も、今日は クラブ活動を 中止しなければ ならない。",
          "今日の 午後の 授業が あるか どうか、10時に メールが 届く。",
          "10時に メールが 届いたら、今日の 午後の 授業は ある。"
        ],
        "answer": 2,
        "explanation": "오전 수업은 취소됐고, 오후 수업 여부는 10시에 오는 메일을 확인해야 해요."
      },
      {
        "id": "n3-r2",
        "source": "N3R p2",
        "title": "휴대전화에 대한 생각",
        "korean": "편리하지만 항상 신경 써야 하는 생활이 싫어서 갖고 싶지 않다는 의견이에요.",
        "tone": "tone-gold",
        "passageStyle": "plain",
        "passage": [
          "「携帯電話は 持っていないんです。」と 私が そう 言うと、たいていの 人は 驚く。",
          "それは 私も よく わかっている。実は、私も 以前、携帯電話を 持っていた。",
          "しかし、いつでも どこにいても 電話に 出なければ いけない 気がして、それが いやで 持つのを やめてしまったのだ。",
          "最近は 料金が 安い ものも あるし、携帯電話が ない 生活には 不便な ことも ある。それでも、私は 今のままで いいと 思っている。"
        ],
        "question": "携帯電話について、「私」は どのように 考えて いますか。",
        "options": [
          "便利だと 言う 人も いるが、自分は そう 思わないので、今は 持つ つもりは ない。",
          "便利だと 思うが、いつも 電話を 気にする 生活は いやなので、今は 持つ つもりは ない。",
          "持っていると 便利だし、最近は 料金が 安くなったので、もう 一度 持つ つもりだ。",
          "持ちたくは なかったが、ないと 不便なので、もう 一度 持つ つもりだ。"
        ],
        "answer": 1,
        "explanation": "편리함은 인정하지만 항상 전화를 의식하는 생활이 싫어서 지금은 다시 가질 생각이 없어요."
      },
      {
        "id": "n3-r3",
        "source": "N3R p3",
        "title": "따뜻한 음료 자판기",
        "korean": "겨울에도 따뜻한 음료를 살 수 있는 자판기가 생긴 이유를 묻는 문제예요.",
        "tone": "tone-sky",
        "passageStyle": "plain",
        "passage": [
          "日本には 飲み物の 自動販売機が たくさん ある。",
          "しかし、最初のころの 自動販売機は、冷たい 物しか 売ることが できなかった。",
          "ある 冬の日、高速道路の 駐車場で、トラックの 運転手たちが 自動販売機で 買った ジュースを 飲んでいた。",
          "みんな とても 寒そうだったので、それを 見た 飲料会社の 社長が、冬には 温かい 物を 飲んでほしいと 考えた。",
          "それから 10年近く かけて 作られたのが、今の 販売機なのだそうだ。"
        ],
        "question": "今の 販売機が 作られることに なったのは、どうしてですか。",
        "options": [
          "冬に 販売機で 冷たい 物を 買って 飲んだ 社長が、客が 気の毒だと 感じたから",
          "冷たい 物が 買える 販売機が あれば 便利だろうと、社長が 考えたから",
          "温かい 物が 買える 販売機が 欲しいと、運転手たちに 言われたから",
          "温かい 物も 買える 販売機が あれば 喜ばれるだろうと、社長が 考えたから"
        ],
        "answer": 3,
        "explanation": "추운 겨울에 따뜻한 음료도 살 수 있으면 좋겠다고 사장이 생각한 게 계기였어요."
      },
      {
        "id": "n3-r4",
        "source": "N3R p4",
        "title": "설명회 보고 자료",
        "korean": "보고 자료를 손보고 회의 전에 준비해야 하는 일을 묻는 메모예요.",
        "tone": "tone-mint",
        "passageStyle": "note",
        "passage": [
          "パクさん",
          "先週の 新しい 企業向け 説明会の 報告資料を 見ました。内容は わかりやすくて いいと 思います。",
          "明日の 午後、私が 会議に 出て、この 資料を 使って 報告することに なりました。",
          "参加企業の リストも 欲しいので、準備しておいて ください。",
          "明日は、モリムラ工業に 寄ってから 出勤するので、会社に 着くのは 11時ごろに なる 予定です。それまでに お願いします。"
        ],
        "question": "この メモを 読んで、パクさんが しなければ ならないことは 何ですか。",
        "options": [
          "11時ごろ までに、説明会に 参加した 企業の リストを 準備しておく。",
          "午後の 会議までに、説明会の 報告資料を わかりやすく 書き直す。",
          "午後の 会議までに 報告資料を 直し、会議で 説明会に ついて 報告する。",
          "黒田課長が モリムラ工業に 行く までに、説明会の 報告資料を 完成させる。"
        ],
        "answer": 3,
        "explanation": "보고 자료와 준비물은 오전 11시 전까지 필요하고, 회의에서 직접 보고하는 사람은 パクさん이 아니라 黒田課長이에요."
      },
      {
        "id": "n3-r5",
        "source": "N3 PDF q24",
        "title": "学校説明会のメール",
        "korean": "학교 설명회 메일을 읽고 김 씨가 해야 할 일을 고르는 문제예요.",
        "tone": "tone-coral",
        "passageStyle": "note",
        "passage": [
          "これは日本語学校からキムさんに届いたメールである。",
          "あて先：kim12@yamanaka-jls.jp",
          "件名：学校説明会につきまして",
          "送信日時：2020年10月8日 10:00",
          "キム様",
          "やまなか日本語学校の田中です。お問い合わせありがとうございます。",
          "来年度の入学希望者を対象にした学校説明会は11月19日(木)と11月22日(日)に開く予定です。",
          "参加を希望される場合は、メールでお申し込みください。申し込み期間は10月7日(水)の9時から11月15日(日)の17時までです。",
          "説明会当日は、バスや電車でお越しください。駐車場はございません。また、受付場所は事務室の前の掲示板でご確認ください。"
        ],
        "question": "このメールを読んで、キムさんがしなければならないことは何か。",
        "options": [
          "11月19日から11月22日の間に来年度の入学申し込みをする。",
          "11月15日までに説明会に参加したいというメールを送る。",
          "説明会の日に車を運転して学校に行く。",
          "説明会の日に事務室の人に受付はどこでするか聞く。"
        ],
        "answer": 1,
        "explanation": "설명회 참가 희망자는 11월 15일 17시까지 메일로 신청해야 한다고 메일에 적혀 있습니다."
      },
      {
        "id": "n3-r6",
        "source": "N3 PDF q25",
        "title": "睡眠の考え方",
        "korean": "수면에 대한 글쓴이의 생각을 고르는 문제예요.",
        "tone": "tone-gold",
        "passageStyle": "plain",
        "passage": [
          "人間は1日7時間寝るべきだと言われている。睡眠不足の状態が続くと、体重が増えたり、病気になったりする可能性が高くなるそうだ。しかし、わずかだが、1日3〜4時間しか寝ないのに健康でいられる人もいるという。忙しい現代人の多くは普通の人より何時間も多く活動できる彼らをうらやましがるだろうが、私は個人個人に合った時間寝て、健康に過ごすことが何より大切ではないだろうかと思う。"
        ],
        "question": "睡眠について、この文章を書いた人はどのように考えているか。",
        "options": [
          "みんな必ず1日7時間は寝るべきだ。",
          "3〜4時間しか寝られなくてもしかたない。",
          "短い睡眠でも元気な人が多くてうらやましい。",
          "人より長く活動することより、ちゃんと寝て健康でいることが重要だ。"
        ],
        "answer": 3,
        "explanation": "글쓴이는 사람마다 맞는 시간만큼 자고 건강하게 지내는 것이 가장 중요하다고 말합니다."
      },
      {
        "id": "n3-r7",
        "source": "N3 PDF q26",
        "title": "生活の中の障害",
        "korean": "생활 속 장애를 없애는 예시가 무엇인지 고르는 문제예요.",
        "tone": "tone-sky",
        "passageStyle": "plain",
        "passage": [
          "高齢者や病気やけがなどで体の不自由な人は、生活する中で不便を感じることが多い。そのため、高齢者が足を高く上げなくても乗れるバスや車いすの人でも入れるトイレが作られた。しかし、まだ課題は多い。近年スマホなどの便利な機器が登場したが、お年寄りや目の見えない人にとっては使いにくいこともある。これからは科学技術の発達と生活の中の障害をなくすことを同時に実現させて、みんなが快適に過ごせる社会になってほしい。"
        ],
        "question": "この文章では生活の中の障害をなくすことは例えばどんなものだと言っているか。",
        "options": [
          "体の不自由な人が使いやすいトイレを作ること",
          "お年寄りがバスに乗れるぐらい元気になること",
          "高齢者の力でスマホに関する課題を解決すること",
          "目が見えなくなったらスマホが使えなくなること"
        ],
        "answer": 0,
        "explanation": "본문 초반에 휠체어 이용자도 들어갈 수 있는 화장실 같은 예를 직접 제시하고 있습니다."
      },
      {
        "id": "n3-r8",
        "source": "N3 PDF q27",
        "title": "ごみ出しのお願い",
        "korean": "쓰레기 배출 안내문을 읽고 타파 씨가 해야 할 일을 고르는 문제예요.",
        "tone": "tone-mint",
        "passageStyle": "note",
        "passage": [
          "タパさんが住んでいるマンションの入口に貼り紙が貼ってあった。",
          "ごみ出しに関するお願い",
          "近くの住人の方々から、当マンションのごみ出しについて苦情が出ております。",
          "1. 普通ごみを出す日は火曜日と金曜日ですが、朝9時以降は出さないようにお願いします。",
          "2. 食べ物のごみは水を切ってください。",
          "3. 普通ごみを捨てる日に電気製品や家具などを捨てることはできません。市役所に連絡し、指定された日時に出してください。",
          "ご協力お願いいたします。 管理事務所"
        ],
        "question": "この貼り紙を読んで、タパさんがしなければならないことは何か。",
        "options": [
          "火曜日と金曜日は朝9時を過ぎてからごみを捨てるようにする。",
          "食べ物のごみを水がある状態のまま捨てないようにする。",
          "本棚を捨てる際は、市役所に捨てた日と時間を報告する。",
          "普通ごみを捨てなければいけない時は、市役所に電話する。"
        ],
        "answer": 1,
        "explanation": "안내문 2번에 음식물 쓰레기는 물기를 빼 달라고 되어 있으므로 물이 있는 채로 버리면 안 됩니다."
      },
      {
        "id": "n3-r9",
        "source": "N3 PDF q28",
        "title": "子どもの育て方 1",
        "korean": "육아 글에서 글쓴이가 '이렇게 말하고 싶다'고 한 내용을 고르는 문제예요.",
        "tone": "tone-coral",
        "passageStyle": "plain",
        "passage": [
          "この間、電車の中で騒いでいた子どもを母親が叱っていた。今の子育ては子どもを叱りすぎていると思う。だから私はこう言いたい。子どもを叱りながら育てるのではなく、子どもを叱らなくてもいいように育ててはどうだろうかと。",
          "子どもは叱られ続けると、大人の言葉を聞かなくなる。考えてみてほしい。大人だって会社の上司から毎日叱られたら、上司の言葉を（　　　）。",
          "子どもには自分を守ってくれる親の気持ちを理解する能力がある。だから、子どもがよくないことをしたら、親は「困る」とか「悲しい」と気持ちを明確に言葉で伝えるべきだ。もちろん、いいことに対しては、いい感情を積極的に伝える。子どもは親と感情が共有できるようになると、親を困らせる行動をしなくなる。私はこういう言葉を「心の言葉」と呼んでいる。"
        ],
        "question": "①こう言いたいとあるが、何か。",
        "options": [
          "たとえ子どもでも電車の中では騒いではいけないと言いたい。",
          "今の親はみんなの前で子どもを叱りすぎていると言いたい。",
          "今も子どもは叱られながら大きくなるものだと言いたい。",
          "子どもを叱る必要がないように育てるべきだと言いたい。"
        ],
        "answer": 3,
        "explanation": "글쓴이는 아이를 꾸짖는 일이 필요 없도록 키우는 쪽이 더 낫다고 주장합니다."
      },
      {
        "id": "n3-r10",
        "source": "N3 PDF q29",
        "title": "子どもの育て方 2",
        "korean": "육아 글의 빈칸에 들어갈 표현을 고르는 문제예요.",
        "tone": "tone-gold",
        "passageStyle": "plain",
        "passage": [
          "この間、電車の中で騒いでいた子どもを母親が叱っていた。今の子育ては子どもを叱りすぎていると思う。だから私はこう言いたい。子どもを叱りながら育てるのではなく、子どもを叱らなくてもいいように育ててはどうだろうかと。",
          "子どもは叱られ続けると、大人の言葉を聞かなくなる。考えてみてほしい。大人だって会社の上司から毎日叱られたら、上司の言葉を（　　　）。",
          "子どもには自分を守ってくれる親の気持ちを理解する能力がある。だから、子どもがよくないことをしたら、親は「困る」とか「悲しい」と気持ちを明確に言葉で伝えるべきだ。もちろん、いいことに対しては、いい感情を積極的に伝える。子どもは親と感情が共有できるようになると、親を困らせる行動をしなくなる。私はこういう言葉を「心の言葉」と呼んでいる。"
        ],
        "question": "②（　　　）に入れるのによいものはどれか。",
        "options": [
          "聞きたくなくなるに違いない",
          "聞こうとするようになるはずだ",
          "聞きたくないことはないだろう",
          "聞かせてもらいたいわけだ"
        ],
        "answer": 0,
        "explanation": "매일 혼나면 상사의 말을 듣고 싶지 않게 된다는 흐름이므로 1번이 자연스럽습니다."
      },
      {
        "id": "n3-r11",
        "source": "N3 PDF q30",
        "title": "子どもの育て方 3",
        "korean": "육아 글에서 말하는 '마음의 언어'의 예를 고르는 문제예요.",
        "tone": "tone-sky",
        "passageStyle": "plain",
        "passage": [
          "この間、電車の中で騒いでいた子どもを母親が叱っていた。今の子育ては子どもを叱りすぎていると思う。だから私はこう言いたい。子どもを叱りながら育てるのではなく、子どもを叱らなくてもいいように育ててはどうだろうかと。",
          "子どもは叱られ続けると、大人の言葉を聞かなくなる。考えてみてほしい。大人だって会社の上司から毎日叱られたら、上司の言葉を（　　　）。",
          "子どもには自分を守ってくれる親の気持ちを理解する能力がある。だから、子どもがよくないことをしたら、親は「困る」とか「悲しい」と気持ちを明確に言葉で伝えるべきだ。もちろん、いいことに対しては、いい感情を積極的に伝える。子どもは親と感情が共有できるようになると、親を困らせる行動をしなくなる。私はこういう言葉を「心の言葉」と呼んでいる。"
        ],
        "question": "この文章では③心の言葉とは、例えばどんなものだと言っているか。",
        "options": [
          "親が叱りたくないのに子どもに「騒ぐな」と言うこと",
          "子どもが悪いことをしても親が「いいよ」と言うこと",
          "子どもがいいことをしたら親が「うれしい」と言うこと",
          "親が「悲しい」と言ったら子どもも「悲しい」と言うこと"
        ],
        "answer": 2,
        "explanation": "좋은 행동에는 부모가 좋은 감정을 적극적으로 말해 주는 것도 '마음의 언어'의 예라고 설명합니다."
      },
      {
        "id": "n3-r12",
        "source": "N3 PDF q31",
        "title": "ゲームの趣味 1",
        "korean": "게임에 대한 '사물의 일면'이 무엇인지 고르는 문제예요.",
        "tone": "tone-mint",
        "passageStyle": "plain",
        "passage": [
          "この間初めて会った人に「趣味は何ですか。」と聞いたら、「恥ずかしいんですけど、ゲームです」と言われた。確かにゲームというと、「目が悪くなる」、「性格が暗そう」などと言って批判する人が多いのが現状だ。しかし、なぜ映画や音楽はよくて、ゲームは恥ずかしい趣味なのだろうか。私たちは物事の一面だけを見て判断していないだろうか。",
          "ある有名なスポーツ選手は、厳しい練習の後にゲームを楽しむという。リラックスできるのはもちろん、集中力も高くなるので、ゲームをするとむしろ調子が上がるそうだ。彼のように誤解されることのない生活を送っていれば、ゲームが趣味だということを恥ずかしく思う必要はないのではないかと思う。",
          "ただ、さっきも言ったように、まだ社会の目は無視できない。相手や状況によっては伝え方を工夫する必要があるだろう。"
        ],
        "question": "①物事の一面とあるが、何か。",
        "options": [
          "初めて会ったときに趣味についてしか聞かないこと",
          "目が悪くなるとわかっていながらもゲームをすること",
          "ゲームに対してよくないイメージしか持たないこと",
          "映画や音楽などもあるのに趣味がゲームしかないこと"
        ],
        "answer": 2,
        "explanation": "글쓴이는 게임을 나쁘게만 보는 시선이 '한 면만 보는 것'이라고 말합니다."
      },
      {
        "id": "n3-r13",
        "source": "N3 PDF q32",
        "title": "ゲームの趣味 2",
        "korean": "오해받지 않는 생활의 예가 무엇인지 고르는 문제예요.",
        "tone": "tone-coral",
        "passageStyle": "plain",
        "passage": [
          "この間初めて会った人に「趣味は何ですか。」と聞いたら、「恥ずかしいんですけど、ゲームです」と言われた。確かにゲームというと、「目が悪くなる」、「性格が暗そう」などと言って批判する人が多いのが現状だ。しかし、なぜ映画や音楽はよくて、ゲームは恥ずかしい趣味なのだろうか。私たちは物事の一面だけを見て判断していないだろうか。",
          "ある有名なスポーツ選手は、厳しい練習の後にゲームを楽しむという。リラックスできるのはもちろん、集中力も高くなるので、ゲームをするとむしろ調子が上がるそうだ。彼のように誤解されることのない生活を送っていれば、ゲームが趣味だということを恥ずかしく思う必要はないのではないかと思う。",
          "ただ、さっきも言ったように、まだ社会の目は無視できない。相手や状況によっては伝え方を工夫する必要があるだろう。"
        ],
        "question": "この文章では②誤解されることのない生活は、例えばどんなものだと言っているか。",
        "options": [
          "仕事や勉強をする前ではなく、した後にゲームを楽しむこと",
          "ゲームをしていても、仕事や勉強できちんと結果を出すこと",
          "ゲームだけでなくスポーツなどの他の趣味も持つこと",
          "ゲームをはじめとしていろいろな分野で有名になること"
        ],
        "answer": 1,
        "explanation": "운동선수 사례처럼 게임을 해도 실제 생활과 일에서 좋은 결과를 내면 오해받지 않는다고 설명합니다."
      },
      {
        "id": "n3-r14",
        "source": "N3 PDF q33",
        "title": "ゲームの趣味 3",
        "korean": "게임 취미에 대한 글쓴이의 생각을 고르는 문제예요.",
        "tone": "tone-gold",
        "passageStyle": "plain",
        "passage": [
          "この間初めて会った人に「趣味は何ですか。」と聞いたら、「恥ずかしいんですけど、ゲームです」と言われた。確かにゲームというと、「目が悪くなる」、「性格が暗そう」などと言って批判する人が多いのが現状だ。しかし、なぜ映画や音楽はよくて、ゲームは恥ずかしい趣味なのだろうか。私たちは物事の一面だけを見て判断していないだろうか。",
          "ある有名なスポーツ選手は、厳しい練習の後にゲームを楽しむという。リラックスできるのはもちろん、集中力も高くなるので、ゲームをするとむしろ調子が上がるそうだ。彼のように誤解されることのない生活を送っていれば、ゲームが趣味だということを恥ずかしく思う必要はないのではないかと思う。",
          "ただ、さっきも言ったように、まだ社会の目は無視できない。相手や状況によっては伝え方を工夫する必要があるだろう。"
        ],
        "question": "「ゲーム」について、この文章を書いた人はどう思っているか。",
        "options": [
          "ゲームをすると必ず目が悪くなるので、やめたほうがいい。",
          "ゲームは音楽や映画より、もっといい趣味である。",
          "恥ずかしがることではないが、社会の視線を無視することは難しい。",
          "有名な人のおかげでどんどんイメージがよくなってきている。"
        ],
        "answer": 2,
        "explanation": "글쓴이는 게임 자체를 부끄러워할 필요는 없지만, 사회의 시선을 완전히 무시할 수는 없다고 봅니다."
      },
      {
        "id": "n3-r15",
        "source": "N3 PDF q34",
        "title": "SNSの嘘ニュース 1",
        "korean": "SNS의 거짓 뉴스 특징에 대해 묻는 문제예요.",
        "tone": "tone-sky",
        "passageStyle": "plain",
        "passage": [
          "私たちはテレビや新聞、そしてインターネットで伝えられるニュースを常に本当であると思って見たり聞いたりしているはずだ。しかし、最近SNSで嘘のニュースが広められることが問題になっている。",
          "例えば、以前「地震で動物園からライオンが町に逃げ出した」という嘘のニュースがSNSで流れたせいで、ある町が大騒ぎになったことがある。本当のニュースのようでありながらも、オーバーな表現を使って、読む人の気持ちや行動を混乱させるのが、嘘のニュースの特徴だ。そして、人々がそれを見て「信じられない！」、「本当に！？」と驚いた後にするのは普通なら確認することだろう。しかし、実際にするのは広めることなのだ。なぜそうするかというと、多くの人は「自分だけがそのニュースを知っていた」、「そのニュースを誰よりも早くみんなに教えてあげられた」ということによって、自分はすごいとか社会から認められていると思いたいからだ。",
          "誰が嘘のニュースを流したかは簡単にわかってしまうし、ネットなのでずっと残ってしまう。それで、周りの人たちからいじめられたり、会社の面接で落とされたりして、それまで何の問題もなかった人の日常が突然変わってしまったということも実際起こっている。",
          "SNSを使うべきではないとは言わない。使い方次第だ。SNSのニュースを見たら、まずは慌てないことだ。そして、いくつかニュースを見比べてみよう。そうすると、何が本当かだんだんわかってくる。軽い気持ちから大切な人生をだめにすることがないようにしたいものだ。"
        ],
        "question": "この文章から「SNSの嘘のニュース」についてわかることは何か。",
        "options": [
          "テレビより早く知ることができるのでいい点もある。",
          "町をにぎやかにしようと思って利用されることもある。",
          "読んで、嘘かどうかをすぐに判断するのが難しい。",
          "誰がはじめに流したかは調べることができない。"
        ],
        "answer": 2,
        "explanation": "거짓 뉴스는 진짜 뉴스처럼 보이면서 과장된 표현으로 혼란을 주기 때문에 바로 진위를 판단하기 어렵다고 설명합니다."
      },
      {
        "id": "n3-r16",
        "source": "N3 PDF q35",
        "title": "SNSの嘘ニュース 2",
        "korean": "본문의 'そうする'가 무엇을 가리키는지 고르는 문제예요.",
        "tone": "tone-mint",
        "passageStyle": "plain",
        "passage": [
          "私たちはテレビや新聞、そしてインターネットで伝えられるニュースを常に本当であると思って見たり聞いたりしているはずだ。しかし、最近SNSで嘘のニュースが広められることが問題になっている。",
          "例えば、以前「地震で動物園からライオンが町に逃げ出した」という嘘のニュースがSNSで流れたせいで、ある町が大騒ぎになったことがある。本当のニュースのようでありながらも、オーバーな表現を使って、読む人の気持ちや行動を混乱させるのが、嘘のニュースの特徴だ。そして、人々がそれを見て「信じられない！」、「本当に！？」と驚いた後にするのは普通なら確認することだろう。しかし、実際にするのは広めることなのだ。なぜそうするかというと、多くの人は「自分だけがそのニュースを知っていた」、「そのニュースを誰よりも早くみんなに教えてあげられた」ということによって、自分はすごいとか社会から認められていると思いたいからだ。",
          "誰が嘘のニュースを流したかは簡単にわかってしまうし、ネットなのでずっと残ってしまう。それで、周りの人たちからいじめられたり、会社の面接で落とされたりして、それまで何の問題もなかった人の日常が突然変わってしまったということも実際起こっている。",
          "SNSを使うべきではないとは言わない。使い方次第だ。SNSのニュースを見たら、まずは慌てないことだ。そして、いくつかニュースを見比べてみよう。そうすると、何が本当かだんだんわかってくる。軽い気持ちから大切な人生をだめにすることがないようにしたいものだ。"
        ],
        "question": "①そうするとあるが、何か。",
        "options": [
          "ライオンは地震が起きると逃げること",
          "町の人がライオンを見て騒ぐこと",
          "嘘のニュースを見てびっくりすること",
          "嘘のニュースを他の人に伝えること"
        ],
        "answer": 3,
        "explanation": "사람들이 놀란 뒤 실제로 하는 행동은 확인이 아니라 퍼뜨리는 것이라고 본문이 말합니다."
      },
      {
        "id": "n3-r17",
        "source": "N3 PDF q36",
        "title": "SNSの嘘ニュース 3",
        "korean": "소중한 인생을 망친다는 말이 무엇인지 고르는 문제예요.",
        "tone": "tone-coral",
        "passageStyle": "plain",
        "passage": [
          "私たちはテレビや新聞、そしてインターネットで伝えられるニュースを常に本当であると思って見たり聞いたりしているはずだ。しかし、最近SNSで嘘のニュースが広められることが問題になっている。",
          "例えば、以前「地震で動物園からライオンが町に逃げ出した」という嘘のニュースがSNSで流れたせいで、ある町が大騒ぎになったことがある。本当のニュースのようでありながらも、オーバーな表現を使って、読む人の気持ちや行動を混乱させるのが、嘘のニュースの特徴だ。そして、人々がそれを見て「信じられない！」、「本当に！？」と驚いた後にするのは普通なら確認することだろう。しかし、実際にするのは広めることなのだ。なぜそうするかというと、多くの人は「自分だけがそのニュースを知っていた」、「そのニュースを誰よりも早くみんなに教えてあげられた」ということによって、自分はすごいとか社会から認められていると思いたいからだ。",
          "誰が嘘のニュースを流したかは簡単にわかってしまうし、ネットなのでずっと残ってしまう。それで、周りの人たちからいじめられたり、会社の面接で落とされたりして、それまで何の問題もなかった人の日常が突然変わってしまったということも実際起こっている。",
          "SNSを使うべきではないとは言わない。使い方次第だ。SNSのニュースを見たら、まずは慌てないことだ。そして、いくつかニュースを見比べてみよう。そうすると、何が本当かだんだんわかってくる。軽い気持ちから大切な人生をだめにすることがないようにしたいものだ。"
        ],
        "question": "②大切な人生をだめにすることとあるが、何か。",
        "options": [
          "生きている間に一度も嘘のニュースを見ないこと",
          "嘘のニュースを流した人を探していじめること",
          "これまでのように普通に生きられなくなること",
          "どのニュースが本当か怠けて一度も調べないこと"
        ],
        "answer": 2,
        "explanation": "거짓 뉴스를 퍼뜨린 기록이 남아서 괴롭힘이나 면접 탈락을 겪으며 평범한 일상이 무너질 수 있다고 설명합니다."
      },
      {
        "id": "n3-r18",
        "source": "N3 PDF q37",
        "title": "SNSの嘘ニュース 4",
        "korean": "SNS 사용에 대한 글쓴이의 생각을 고르는 문제예요.",
        "tone": "tone-gold",
        "passageStyle": "plain",
        "passage": [
          "私たちはテレビや新聞、そしてインターネットで伝えられるニュースを常に本当であると思って見たり聞いたりしているはずだ。しかし、最近SNSで嘘のニュースが広められることが問題になっている。",
          "例えば、以前「地震で動物園からライオンが町に逃げ出した」という嘘のニュースがSNSで流れたせいで、ある町が大騒ぎになったことがある。本当のニュースのようでありながらも、オーバーな表現を使って、読む人の気持ちや行動を混乱させるのが、嘘のニュースの特徴だ。そして、人々がそれを見て「信じられない！」、「本当に！？」と驚いた後にするのは普通なら確認することだろう。しかし、実際にするのは広めることなのだ。なぜそうするかというと、多くの人は「自分だけがそのニュースを知っていた」、「そのニュースを誰よりも早くみんなに教えてあげられた」ということによって、自分はすごいとか社会から認められていると思いたいからだ。",
          "誰が嘘のニュースを流したかは簡単にわかってしまうし、ネットなのでずっと残ってしまう。それで、周りの人たちからいじめられたり、会社の面接で落とされたりして、それまで何の問題もなかった人の日常が突然変わってしまったということも実際起こっている。",
          "SNSを使うべきではないとは言わない。使い方次第だ。SNSのニュースを見たら、まずは慌てないことだ。そして、いくつかニュースを見比べてみよう。そうすると、何が本当かだんだんわかってくる。軽い気持ちから大切な人生をだめにすることがないようにしたいものだ。"
        ],
        "question": "SNSについてこの文章を書いた人はどう考えているか。",
        "options": [
          "テレビや新聞より嘘のニュースが多いので使ってはいけない。",
          "社会から認められたいと思っている人はぜひ使うべきだ。",
          "使ってもいいが、内容が本当かどうか注意したほうがいい。",
          "嘘のニュースを消すことができないうちは使わないほうがいい。"
        ],
        "answer": 2,
        "explanation": "글쓴이는 SNS 자체를 금지해야 한다기보다, 여러 뉴스를 비교하며 진위를 확인하면서 써야 한다고 봅니다."
      },
      {
        "id": "n3-r19",
        "source": "N3 PDF q38",
        "title": "春のプログラム 1",
        "korean": "문화센터 프로그램 안내를 보고 아란 씨가 내야 할 금액을 고르는 문제예요.",
        "tone": "tone-sky",
        "passageStyle": "note",
        "passage": [
          "川上市文化センター 外国人住民のための春のプログラム",
          "【Aコース】高岡山の歴史ツアー / 対象: 18歳以上の健康な方 / 日時: 4月18日(土) 9時-16時 / 集合場所: 川上市文化センター1階ロビー / 参加費: 4,000円 / 昼食あり / 弁当持参なら800円引き / 資料代100円は当日現金",
          "【Bコース】河梨湖ハイキングツアー / 対象: 小学生のお子様とそのご両親、ご兄弟 / 日時: 4月19日(日) 11時-15時 / 集合場所: 河梨湖駅前 / 参加費: 1,500円 / 小学生以下無料 / 弁当持参",
          "【Cコース】小学生のための日本文化「書道」体験 / 対象: 小学生 / 日時: 4月21日(水) 16時-17時半 / 集合場所: 川上市文化センター3階大会議室 / 参加費: 200円 / お父様またはお母様とお越しください",
          "お問い合わせ: 川上市文化センター事務室 011-1234-5678"
        ],
        "question": "アランさんは全部でいくら払わなければいけないか。",
        "options": [
          "4,900円",
          "4,800円",
          "4,100円",
          "3,300円"
        ],
        "answer": 2,
        "explanation": "A코스 참가비 4,000엔에 자료비 100엔이 더해지고, 도시락을 가져오지 않으므로 할인은 없습니다."
      },
      {
        "id": "n3-r20",
        "source": "N3 PDF q39",
        "title": "春のプログラム 2",
        "korean": "문화센터 프로그램 안내를 보고 응우옌 씨가 딸을 위해 해야 할 일을 고르는 문제예요.",
        "tone": "tone-mint",
        "passageStyle": "note",
        "passage": [
          "川上市文化センター 外国人住民のための春のプログラム",
          "【Aコース】高岡山の歴史ツアー / 対象: 18歳以上の健康な方 / 日時: 4月18日(土) 9時-16時 / 集合場所: 川上市文化センター1階ロビー / 参加費: 4,000円 / 昼食あり / 弁当持参なら800円引き / 資料代100円は当日現金",
          "【Bコース】河梨湖ハイキングツアー / 対象: 小学生のお子様とそのご両親、ご兄弟 / 日時: 4月19日(日) 11時-15時 / 集合場所: 河梨湖駅前 / 参加費: 1,500円 / 小学生以下無料 / 弁当持参",
          "【Cコース】小学生のための日本文化「書道」体験 / 対象: 小学生 / 日時: 4月21日(水) 16時-17時半 / 集合場所: 川上市文化センター3階大会議室 / 参加費: 200円 / お父様またはお母様とお越しください",
          "お問い合わせ: 川上市文化センター事務室 011-1234-5678"
        ],
        "question": "グエンさんが娘のためにしてあげなければいけないことは何か。",
        "options": [
          "資料代を持たせてあげる。",
          "お弁当を作ってあげる。",
          "白い靴下を買ってあげる。",
          "当日一緒に行ってあげる。"
        ],
        "answer": 3,
        "explanation": "평일에 가능한 코스는 C코스이고, C코스는 보호자가 함께 와야 한다고 적혀 있습니다."
      }
    ]
  }
}
